omero_openlink/__init__.py
omero_openlink/apps.py
omero_openlink/openlink_settings.py
omero_openlink/urls.py
omero_openlink/views.py
omero_openlink/scripts/nginx/autoIndexStyle.xslt
omero_openlink/scripts/omero/util_scripts/Create_OpenLink.py
omero_openlink/templates/omero_openlink/index.html
omero_openlink/templates/omero_openlink/webclient_plugins/right_plugin.openlink.js.html
omero_openlink-2.0.0.dist-info/LICENSE
omero_openlink-2.0.0.dist-info/METADATA
omero_openlink-2.0.0.dist-info/WHEEL
omero_openlink-2.0.0.dist-info/top_level.txt
omero_openlink-2.0.0.dist-info/RECORD
