Metadata-Version: 2.1
Name: omero-openlink
Version: 2.0.0
Summary: OMERO.openlink app
Home-page: https://github.com/sukunis/OMERO.openlink
Download-URL: https://github.com/sukunis/OMERO.openlink/archive/v2.0.0.tar.gz
Author: sukunis
Author-email: sinukesus@gmail.com
Maintainer: sukunis
License: GNU Affero General Public License v3.0
Keywords: OMERO.web,plugin,openlink
Classifier: Development Status :: 5 - Production/Stable
Classifier: Environment :: Web Environment
Classifier: Framework :: Django
Classifier: Intended Audience :: End Users/Desktop
Classifier: Intended Audience :: Science/Research
Classifier: Natural Language :: English
Classifier: Operating System :: OS Independent
Classifier: Programming Language :: JavaScript
Classifier: Programming Language :: Python :: 3
Classifier: Topic :: Internet :: WWW/HTTP
Classifier: Topic :: Internet :: WWW/HTTP :: Dynamic Content
Classifier: Topic :: Internet :: WWW/HTTP :: WSGI
Classifier: Topic :: Scientific/Engineering :: Visualization
Classifier: Topic :: Software Development :: Libraries :: Application Frameworks
Classifier: Topic :: Text Processing :: Markup :: HTML
Requires-Python: >=3
License-File: LICENSE
Requires-Dist: omero-web>=5.6.0
